helix/VERSION.py
helix/configuration.py
helix/converter.py
helix/main.py
helix/adapters/__init__.py
helix/adapters/alignment_map_file_info_adapter.py
helix/adapters/alignment_stats_adapter.py
helix/adapters/coverage_stats_adapter.py
helix/adapters/genome_adapter.py
helix/adapters/header_adapter.py
helix/adapters/index_stats_adapter.py
helix/adapters/reference_adapter.py
helix/adapters/search.py
helix/alignment_map/__init__.py
helix/alignment_map/alignment_map_file.py
helix/alignment_map/alignment_map_header.py
helix/alignment_map/alignment_map_row.py
helix/alignment_map/alignment_stats_calculator.py
helix/alignment_map/coverage_stats_calculator.py
helix/alignment_map/index_stats_calculator.py
helix/alignment_map/variant_caller.py
helix/data/__init__.py
helix/data/alignment_stats.py
helix/data/build.py
helix/data/chromosome_name_type.py
helix/data/coverage_stats.py
helix/data/extract_target_format.py
helix/data/file_type.py
helix/data/gender.py
helix/data/genome.py
helix/data/microarray_converter.py
helix/data/mitochondrial_model.py
helix/data/mitochondrial_model_type.py
helix/data/mitochondrial_name_type.py
helix/data/read_type.py
helix/data/sequence.py
helix/data/sequence_type.py
helix/data/sorting.py
helix/data/source.py
helix/data/tabular_data.py
helix/data/alignment_map/__init__.py
helix/data/alignment_map/alignment_map_file_info.py
helix/data/alignment_map/alignment_map_header_metadata.py
helix/data/alignment_map/alignment_map_header_program.py
helix/data/alignment_map/alignment_map_header_read_group.py
helix/data/alignment_map/alignment_map_header_sequence.py
helix/fasta/__init__.py
helix/fasta/fasta_letter_counter.py
helix/fasta/fasta_stats_files.py
helix/fasta/letter_run.py
helix/fasta/letter_run_buckets.py
helix/fasta/letter_run_collection.py
helix/fastq/__init__.py
helix/fastq/fastq_file.py
helix/files/__init__.py
helix/files/bgzip.py
helix/files/decompressor.py
helix/files/downloader.py
helix/files/file_type_checker.py
helix/files/gzip.py
DoubleHelix-1.0.0a7.dist-info/LICENSE
DoubleHelix-1.0.0a7.dist-info/METADATA
DoubleHelix-1.0.0a7.dist-info/WHEEL
DoubleHelix-1.0.0a7.dist-info/entry_points.txt
DoubleHelix-1.0.0a7.dist-info/top_level.txt
DoubleHelix-1.0.0a7.dist-info/RECORD
