Metadata-Version: 2.1
Name: DoubleHelix
Version: 1.0.0a7
Summary: Genomic data manipulation tool
Author-email: chaplin89 <hello@doublehelix.app>
License: GNU GENERAL PUBLIC LICENSE
Project-URL: Documentation, https://doublehelix.app
Project-URL: homepage, https://github.com/DoubleHelixApp/DoubleHelix
Project-URL: Repository, https://github.com/DoubleHelixApp/DoubleHelix
Project-URL: Issues, https://github.com/DoubleHelixApp/DoubleHelix/issues
Project-URL: Changelog, https://github.com/DoubleHelixApp/DoubleHelix/releases
Keywords: bioinformatics,genetics,wgs,microarray,science
Classifier: Development Status :: 3 - Alpha
Classifier: Environment :: Console
Classifier: Environment :: X11 Applications :: Qt
Classifier: Environment :: Win32 (MS Windows)
Classifier: Intended Audience :: Developers
Classifier: Intended Audience :: Science/Research
Classifier: License :: OSI Approved :: BSD License
Classifier: License :: OSI Approved :: MIT License
Classifier: Operating System :: OS Independent
Classifier: Programming Language :: Python :: 3.12
Classifier: Topic :: Scientific/Engineering :: Bio-Informatics
License-File: LICENSE
Requires-Dist: setuptools
Requires-Dist: pefile
Requires-Dist: pycurl
Requires-Dist: tqdm
Requires-Dist: google-cloud-storage
Requires-Dist: sphinx
Requires-Dist: pytest
Requires-Dist: pyinstaller
Requires-Dist: PySide6
Requires-Dist: jinja2
Requires-Dist: vcf-parser
Requires-Dist: sentry-sdk
Requires-Dist: debugpy
Requires-Dist: psutil
Requires-Dist: pydantic
Requires-Dist: certifi
Requires-Dist: parse
Requires-Dist: doublehelix-external ==v0.0.2 ; platform_system == "Windows"
Requires-Dist: pypiwin32 ; platform_system == "Windows"
